radio_mlbee/__init__.py
radio_mlbee/__main__.py
radio_mlbee/__main__.py-
radio_mlbee/app.py
radio_mlbee/cos_matrix2.py
radio_mlbee/data/sternstunden04-de.txt
radio_mlbee/data/sternstunden04-en.txt
radio_mlbee/data/test-en.txt
radio_mlbee/data/test-zh.txt
radio_mlbee/gen_cmat.py
radio_mlbee/gradio_queue.db
radio_mlbee/loadtext.py
radio_mlbee/radio_mlbee.py
radio_mlbee/utils.py
radio_mlbee-0.1.0a2.dist-info/entry_points.txt
radio_mlbee-0.1.0a2.dist-info/LICENSE
radio_mlbee-0.1.0a2.dist-info/WHEEL
radio_mlbee-0.1.0a2.dist-info/METADATA
radio_mlbee-0.1.0a2.dist-info/RECORD
