Metadata-Version: 2.1
Name: radio-mlbee
Version: 0.1.0a2
Summary: mlbee via gradio
Home-page: https://github.com/ffreemt/radio-mlbee
License: MIT
Author: ffreemt
Requires-Python: >=3.8.3,<4.0.0
Classifier: License :: OSI Approved :: MIT License
Classifier: Programming Language :: Python :: 3
Classifier: Programming Language :: Python :: 3.10
Classifier: Programming Language :: Python :: 3.9
Requires-Dist: aset2pairs (>=0.1.0,<0.2.0)
Requires-Dist: cchardet (>=2.1.7,<3.0.0)
Requires-Dist: cmat2aset (>=0.1.0-alpha.7,<0.2.0)
Requires-Dist: gradio (>=3.0.15,<4.0.0)
Requires-Dist: hf-model-s-cpu (>=0.1.1,<0.2.0)
Requires-Dist: icecream (>=2.1.1,<3.0.0)
Requires-Dist: install (>=1.3.5,<2.0.0)
Requires-Dist: joblib (>=1.1.0,<2.0.0)
Requires-Dist: logzero (>=1.7.0,<2.0.0)
Requires-Dist: more-itertools (>=8.13.0,<9.0.0)
Requires-Dist: seg-text (>=0.1.2,<0.2.0)
Requires-Dist: sentence-transformers (>=2.2.0,<3.0.0)
Requires-Dist: set-loglevel (>=0.1.2,<0.2.0)
Requires-Dist: typer (>=0.4.1,<0.5.0)
Project-URL: Repository, https://github.com/ffreemt/radio-mlbee
